mcp_server_milvus/.mypy_cache/.gitignore
mcp_server_milvus/.mypy_cache/3.12/@plugins_snapshot.json
mcp_server_milvus/.mypy_cache/3.12/__future__.data.json
mcp_server_milvus/.mypy_cache/3.12/__future__.meta.json
mcp_server_milvus/.mypy_cache/3.12/_ast.data.json
mcp_server_milvus/.mypy_cache/3.12/_ast.meta.json
mcp_server_milvus/.mypy_cache/3.12/_asyncio.data.json
mcp_server_milvus/.mypy_cache/3.12/_asyncio.meta.json
mcp_server_milvus/.mypy_cache/3.12/_bisect.data.json
mcp_server_milvus/.mypy_cache/3.12/_bisect.meta.json
mcp_server_milvus/.mypy_cache/3.12/_blake2.data.json
mcp_server_milvus/.mypy_cache/3.12/_blake2.meta.json
mcp_server_milvus/.mypy_cache/3.12/_bz2.data.json
mcp_server_milvus/.mypy_cache/3.12/_bz2.meta.json
mcp_server_milvus/.mypy_cache/3.12/_codecs.data.json
mcp_server_milvus/.mypy_cache/3.12/_codecs.meta.json
mcp_server_milvus/.mypy_cache/3.12/_collections_abc.data.json
mcp_server_milvus/.mypy_cache/3.12/_collections_abc.meta.json
mcp_server_milvus/.mypy_cache/3.12/_compression.data.json
mcp_server_milvus/.mypy_cache/3.12/_compression.meta.json
mcp_server_milvus/.mypy_cache/3.12/_contextvars.data.json
mcp_server_milvus/.mypy_cache/3.12/_contextvars.meta.json
mcp_server_milvus/.mypy_cache/3.12/_ctypes.data.json
mcp_server_milvus/.mypy_cache/3.12/_ctypes.meta.json
mcp_server_milvus/.mypy_cache/3.12/_decimal.data.json
mcp_server_milvus/.mypy_cache/3.12/_decimal.meta.json
mcp_server_milvus/.mypy_cache/3.12/_frozen_importlib.data.json
mcp_server_milvus/.mypy_cache/3.12/_frozen_importlib.meta.json
mcp_server_milvus/.mypy_cache/3.12/_frozen_importlib_external.data.json
mcp_server_milvus/.mypy_cache/3.12/_frozen_importlib_external.meta.json
mcp_server_milvus/.mypy_cache/3.12/_hashlib.data.json
mcp_server_milvus/.mypy_cache/3.12/_hashlib.meta.json
mcp_server_milvus/.mypy_cache/3.12/_io.data.json
mcp_server_milvus/.mypy_cache/3.12/_io.meta.json
mcp_server_milvus/.mypy_cache/3.12/_operator.data.json
mcp_server_milvus/.mypy_cache/3.12/_operator.meta.json
mcp_server_milvus-0.1.1.dev9.dist-info/WHEEL
mcp_server_milvus-0.1.1.dev9.dist-info/entry_points.txt
mcp_server_milvus-0.1.1.dev9.dist-info/METADATA
mcp_server_milvus-0.1.1.dev9.dist-info/RECORD
