Metadata-Version: 2.3
Name: mcp-server-milvus
Version: 0.1.1.dev9
Summary: MCP server for Milvus
Author: D. Danchev
Author-email: D. Danchev <12420863+danchev@users.noreply.github.com>
Classifier: License :: OSI Approved :: Apache Software License
Classifier: Development Status :: 3 - Alpha
Classifier: Operating System :: OS Independent
Classifier: Intended Audience :: Developers
Classifier: Intended Audience :: Financial and Insurance Industry
Classifier: Topic :: Scientific/Engineering
Classifier: Topic :: Scientific/Engineering :: Artificial Intelligence
Classifier: Topic :: Scientific/Engineering :: Interface Engine/Protocol Translator
Classifier: Topic :: Software Development :: Libraries
Classifier: Topic :: Software Development :: Libraries :: Python Modules
Classifier: Programming Language :: Python
Classifier: Programming Language :: Python :: 3
Classifier: Programming Language :: Python :: 3.10
Classifier: Programming Language :: Python :: 3.11
Classifier: Programming Language :: Python :: 3.12
Classifier: Programming Language :: Python :: 3.13
Classifier: Programming Language :: Python :: 3.14
Classifier: Typing :: Typed
Requires-Dist: mcp[cli]>=1.21.0
Requires-Dist: pymilvus>=2.6.3
Requires-Python: >=3.10
Project-URL: Homepage, https://github.com/danchev/mcp-server-milvus
Project-URL: Issues, https://github.com/danchev/mcp-server-milvus/issues
